pypedrivehelper/__init__.py
pypedrivehelper/helper.py
pypedrive_helper-1.0.2.dist-info/LICENSE
pypedrive_helper-1.0.2.dist-info/METADATA
pypedrive_helper-1.0.2.dist-info/WHEEL
pypedrive_helper-1.0.2.dist-info/top_level.txt
pypedrive_helper-1.0.2.dist-info/RECORD
