Metadata-Version: 2.1
Name: pypedrive-helper
Version: 1.0.2
Summary: The Python Pipedrive API Helper
Home-page: https://github.com/kristan-dev/pipedrive_helper
Author: Kristan Eres
Author-email: spectre.aloha@outlook.com
License: MIT
Platform: UNKNOWN
Classifier: License :: OSI Approved :: MIT License
Classifier: Programming Language :: Python :: 3
Classifier: Programming Language :: Python :: 3.7
Classifier: Operating System :: OS Independent
Requires-Python: >=3.6
Requires-Dist: requests
